butter_cms/__init__.py
butter_cms/__version__.py
butter_cms/author.py
butter_cms/category.py
butter_cms/client.py
butter_cms/content_field.py
butter_cms/feed.py
butter_cms/page.py
butter_cms/post.py
butter_cms/tag.py
butter_cms/unit_tests.py
buttercms_python-2.0.dist-info/LICENSE
buttercms_python-2.0.dist-info/METADATA
buttercms_python-2.0.dist-info/WHEEL
buttercms_python-2.0.dist-info/top_level.txt
buttercms_python-2.0.dist-info/RECORD
