Metadata-Version: 2.1
Name: buttercms-python
Version: 2.0
Summary: API First Blogging and CMS platform built for developers
Home-page: https://github.com/buttercms/buttercms-python
Download-URL: https://github.com/buttercms/buttercms-python/tarball/0.1
Author: Adam Yala
Author-email: adam@adamyala.com
Keywords: foo,bar,baz
Classifier: Development Status :: 3 - Alpha
Classifier: Intended Audience :: Developers
Classifier: Environment :: Web Environment
Classifier: Operating System :: OS Independent
Classifier: Programming Language :: Python
Classifier: Programming Language :: Python :: 2.7
Classifier: Framework :: Django
Classifier: Topic :: Software Development :: Build Tools
Classifier: License :: OSI Approved :: MIT License
License-File: LICENSE
Requires-Dist: requests
